fediverse_pasture_inputs/__init__.py
fediverse_pasture_inputs/__main__.py
fediverse_pasture_inputs/config.py
fediverse_pasture_inputs/format.py
fediverse_pasture_inputs/test_available.py
fediverse_pasture_inputs/test_resources.py
fediverse_pasture_inputs/test_types.py
fediverse_pasture_inputs/test_utils.py
fediverse_pasture_inputs/types.py
fediverse_pasture_inputs/utils.py
fediverse_pasture_inputs/version.py
fediverse_pasture_inputs/inputs/__init__.py
fediverse_pasture_inputs/inputs/attachments.py
fediverse_pasture_inputs/inputs/attributed_to.py
fediverse_pasture_inputs/inputs/content_warnings.py
fediverse_pasture_inputs/inputs/context.py
fediverse_pasture_inputs/inputs/emoji.py
fediverse_pasture_inputs/inputs/hashtag_jsonld.py
fediverse_pasture_inputs/inputs/hashtags.py
fediverse_pasture_inputs/inputs/html_anchor.py
fediverse_pasture_inputs/inputs/html_tags.py
fediverse_pasture_inputs/inputs/html_tags_article.py
fediverse_pasture_inputs/inputs/html_tags_bad.py
fediverse_pasture_inputs/inputs/html_tags_base.py
fediverse_pasture_inputs/inputs/html_tags_summary.py
fediverse_pasture_inputs/inputs/image_attachments.py
fediverse_pasture_inputs/inputs/image_description.py
fediverse_pasture_inputs/inputs/in_reply_to.py
fediverse_pasture_inputs/inputs/language.py
fediverse_pasture_inputs/inputs/mentions.py
fediverse_pasture_inputs/inputs/necessary_properties.py
fediverse_pasture_inputs/inputs/object_type.py
fediverse_pasture_inputs/inputs/public.py
fediverse_pasture_inputs/inputs/quotes.py
fediverse_pasture_inputs/inputs/recommended_media_attachments.py
fediverse_pasture_inputs/inputs/url.py
fediverse_pasture_inputs/tool/__init__.py
fediverse_pasture_inputs/tool/format.py
fediverse_pasture_inputs/tool/navigation.py
fediverse_pasture_inputs/tool/task.py
fediverse_pasture_inputs/tool/test_download.py
fediverse_pasture_inputs/tool/test_format.py
fediverse_pasture_inputs/tool/test_navigation.py
fediverse_pasture_inputs/tool/transformer.py
fediverse_pasture_inputs-0.3.3.dist-info/METADATA
fediverse_pasture_inputs-0.3.3.dist-info/WHEEL
fediverse_pasture_inputs-0.3.3.dist-info/RECORD
