Metadata-Version: 2.4
Name: fediverse-pasture-inputs
Version: 0.3.3
Summary: Input data to generate interoperability data from the fediverse-pasture
Project-URL: Homepage, https://funfedi.dev/
Project-URL: Documentation, https://inputs.funfedi.dev/
Project-URL: Repository, https://codeberg.org/funfedidev/fediverse-pasture-inputs
Project-URL: Issues, https://codeberg.org/funfedidev/fediverse-pasture-inputs/issues
Project-URL: Changelog, https://codeberg.org/funfedidev/fediverse-pasture-inputs/src/branch/main/CHANGES.md
Author-email: Helge <helge.krueger@gmail.com>
License-Expression: MIT
Requires-Python: >=3.13
Requires-Dist: fediverse-pasture>=0.2.14
